AntiSpam/AntiSpamHandler.py
AntiSpam/BaseExtension.py
AntiSpam/Exceptions.py
AntiSpam/Guild.py
AntiSpam/Message.py
AntiSpam/User.py
AntiSpam/Util.py
AntiSpam/__init__.py
AntiSpam/static.py
AntiSpam/ext/AntiSpamTracker.py
AntiSpam/ext/__init__.py
Discord_Anti_Spam_Fixed-0.8.0.dist-info/LICENSE
Discord_Anti_Spam_Fixed-0.8.0.dist-info/METADATA
Discord_Anti_Spam_Fixed-0.8.0.dist-info/WHEEL
Discord_Anti_Spam_Fixed-0.8.0.dist-info/top_level.txt
Discord_Anti_Spam_Fixed-0.8.0.dist-info/RECORD
