Metadata-Version: 2.1
Name: Discord-Anti-Spam-Fixed
Version: 0.8.0
Summary: An easy to use package for anti-spam features in discord.py.
Home-page: https://github.com/Skelmis/DPY-Anti-Spam
Author: Tinh
Author-email: ethan@koldfusion.xyz
License: UNKNOWN
Platform: UNKNOWN
Classifier: Programming Language :: Python :: 3
Classifier: License :: OSI Approved :: MIT License
Classifier: Operating System :: OS Independent
Classifier: Development Status :: 4 - Beta
Requires-Python: >=3.6
Requires-Dist: fuzzywuzzy (>=0.18)
Requires-Dist: discord.py (>=1)
